imgscraper/__init__.py
imgscraper/scraper_constructor.py
imgscraper/src/__init__.py
imgscraper/src/core.py
imgscraper/src/models.py
imgscraper/src/scrapers/__init__.py
imgscraper/src/scrapers/bs4_scraper.py
imgscraper/src/scrapers/scraper.py
imgscraper-0.3.0.dist-info/LICENSE
imgscraper-0.3.0.dist-info/METADATA
imgscraper-0.3.0.dist-info/WHEEL
imgscraper-0.3.0.dist-info/top_level.txt
imgscraper-0.3.0.dist-info/RECORD
