Metadata-Version: 2.2
Name: imgscraper
Version: 0.3.0
Summary: Scans web pages for images
Author-email: Dawid Szaniawski <webluduspl@gmail.com>
License: MIT License
Project-URL: Source, https://github.com/dawid-szaniawski/imgscraper
Keywords: api,automation,json,web
Classifier: Development Status :: 3 - Alpha
Classifier: Environment :: Web Environment
Classifier: Intended Audience :: Developers
Classifier: Natural Language :: English
Classifier: Operating System :: OS Independent
Classifier: License :: OSI Approved :: MIT License
Classifier: Programming Language :: Python
Classifier: Programming Language :: Python :: 3.10
Classifier: Programming Language :: Python :: 3.11
Classifier: Programming Language :: Python :: 3 :: Only
Classifier: Programming Language :: Python :: Implementation :: CPython
Classifier: Topic :: Internet :: WWW/HTTP
Classifier: Topic :: Software Development :: Libraries
Classifier: Topic :: Utilities
Classifier: Topic :: File Formats :: JSON
Classifier: Topic :: File Formats :: JSON :: JSON Schema
Classifier: Typing :: Typed
Requires-Python: >=3.10
License-File: LICENSE
Requires-Dist: bepatient==0.17.0
Requires-Dist: requests>=2.28.1
Requires-Dist: beautifulsoup4~=4.12.3
Provides-Extra: dev
Requires-Dist: black~=23.10.1; extra == "dev"
Requires-Dist: flake8~=6.1.0; extra == "dev"
Requires-Dist: isort~=5.12.0; extra == "dev"
Requires-Dist: mypy~=1.6.1; extra == "dev"
Requires-Dist: pylint<=3.0.2; extra == "dev"
Requires-Dist: pylint-pytest~=1.1.3; extra == "dev"
Requires-Dist: pytest~=7.4.2; extra == "dev"
Requires-Dist: pytest-cov~=4.1.0; extra == "dev"
Requires-Dist: pytest-mock~=3.12.0; extra == "dev"
Requires-Dist: responses~=0.25.6; extra == "dev"
Requires-Dist: ruff~=0.1.2; extra == "dev"
Requires-Dist: tox~=4.11.3; extra == "dev"
Requires-Dist: twine~=4.0.2; extra == "dev"
